odoo9_addon_web_send_message_popup-9.0.1.0.0-py2.7-nspkg.pth
odoo_addons/web_send_message_popup/__openerp__.py
odoo_addons/web_send_message_popup/__init__.py
odoo_addons/web_send_message_popup/README.rst
odoo_addons/web_send_message_popup/views/web_send_message_popup.xml
odoo_addons/web_send_message_popup/static/src/js/chatter.js
odoo9_addon_web_send_message_popup-9.0.1.0.0.dist-info/top_level.txt
odoo9_addon_web_send_message_popup-9.0.1.0.0.dist-info/WHEEL
odoo9_addon_web_send_message_popup-9.0.1.0.0.dist-info/RECORD
odoo9_addon_web_send_message_popup-9.0.1.0.0.dist-info/metadata.json
odoo9_addon_web_send_message_popup-9.0.1.0.0.dist-info/DESCRIPTION.rst
odoo9_addon_web_send_message_popup-9.0.1.0.0.dist-info/METADATA
odoo9_addon_web_send_message_popup-9.0.1.0.0.dist-info/namespace_packages.txt
